Metadata-Version: 1.0
Name: eezotop-hist-old
Version: 0.1.0
Summary: Dummy module for doing lab.
Home-page: UNKNOWN
Author: Yegor Zudin
Author-email: zudin.0197@gmail.com
License: UNKNOWN
Platform: UNKNOWN
